MANIFEST.in
README.txt
VERSION.txt
setup.py
tox.ini
bbcu.fastqcReports.egg-info/PKG-INFO
bbcu.fastqcReports.egg-info/SOURCES.txt
bbcu.fastqcReports.egg-info/dependency_links.txt
bbcu.fastqcReports.egg-info/requires.txt
bbcu.fastqcReports.egg-info/top_level.txt
fastqcReports/__init__.py
fastqcReports/logging_conf.py
fastqcReports/reporter.py
fastqcReports/settings.py
fastqcReports/reports/__init__.py
fastqcReports/reports/graph_unavailable.png
fastqcReports/reports/project_report.html
fastqcReports/reports/resources/css/style.css
fastqcReports/reports/resources/images/download.png
fastqcReports/reports/resources/images/info.png
fastqcReports/reports/resources/images/logo.png
fastqcReports/reports/resources/images/view.gif
fastqcReports/test/__init__.py
fastqcReports/test/base.py
fastqcReports/test/reports_tests.py
scripts/run-fastqc-report-table.py
scripts/run-fastqc-report.py