Metadata-Version: 1.0
Name: bbcu.fastqcReports
Version: 1.0.8
Summary: Create summary of FastQC output in html file
Home-page: UNKNOWN
Author: Refael Kohen, Ophir Tal
Author-email: refael.kohen@weizmann.ac.il, ophir.tal@weizmann.ac.il
License: UNKNOWN
Platform: UNKNOWN
